getpassecho/__init__.py
getpassecho-1.0.dist-info/DESCRIPTION.rst
getpassecho-1.0.dist-info/METADATA
getpassecho-1.0.dist-info/RECORD
getpassecho-1.0.dist-info/WHEEL
getpassecho-1.0.dist-info/metadata.json
getpassecho-1.0.dist-info/top_level.txt
