Metadata-Version: 2.0
Name: getpassecho
Version: 1.0
Summary: getpass with an echo char
Home-page: UNKNOWN
Author: Kurt Spindler
Author-email: kespindler@gmail.com
License: UNKNOWN
Platform: UNKNOWN
